ass_tg/__init__.py
ass_tg/entities.py
ass_tg/exceptions.py
ass_tg/i18n.py
ass_tg/middleware.py
ass_tg/types/__init__.py
ass_tg/types/aliases.py
ass_tg/types/base_abc.py
ass_tg/types/entities.py
ass_tg/types/keyvalue.py
ass_tg/types/lists.py
ass_tg/types/logic.py
ass_tg/types/one_of.py
ass_tg/types/oneword.py
ass_tg/types/reverse.py
ass_tg/types/text.py
ass_tg/types/text_eq.py
ass_tg/types/text_rules.py
ass_tg/types/time_arg.py
ass_tg/types/user.py
ass_tg/types/wrapped.py
ass_tg-2.4.3.dist-info/METADATA
ass_tg-2.4.3.dist-info/WHEEL
ass_tg-2.4.3.dist-info/RECORD
