Metadata-Version: 2.3
Name: ass_tg
Version: 2.4.3
Summary: Arguments Stupendous Searcher (ASS)
Author: Yacha
Author-email: yacha@orangefox.tech
Requires-Python: >=3.12,<4.0
Classifier: Programming Language :: Python :: 3
Classifier: Programming Language :: Python :: 3.12
Classifier: Programming Language :: Python :: 3.13
Requires-Dist: Babel (>=2,<3)
Requires-Dist: aiogram (>=3,<4)
Requires-Dist: stfu-tg (>=3.0,<4.0)
